zEvent/__init__.py
zevent-0.0.1.dist-info/METADATA
zevent-0.0.1.dist-info/WHEEL
zevent-0.0.1.dist-info/licenses/LICENSE
zevent-0.0.1.dist-info/RECORD
