Metadata-Version: 2.1
Name: zEvent
Version: 0.0.1
Summary: Simple event library
Author-email: zCloze <zclozethe@gmail.com>
License-File: LICENSE
Classifier: License :: OSI Approved :: MIT License
Classifier: Operating System :: OS Independent
Classifier: Programming Language :: Python :: 3
Requires-Python: >=3.10
